html_plot/__init__.py
html_plot-0.1.4.dist-info/METADATA
html_plot-0.1.4.dist-info/WHEEL
html_plot-0.1.4.dist-info/RECORD
