Metadata-Version: 2.1
Name: html-plot
Version: 0.1.4
Summary: Render Matplotlib plots as HTML objects in Jupyter, so that they can be placed in HTML tables, downloaded on click, and more
Home-page: https://github.com/kxmh42/html-plot
License: OSL-3.0 OR AGPL-3.0-or-later
Author: kxmh42
Author-email: kxmh42@users.noreply.github.com
Requires-Python: >=3.8,<4.0
Classifier: License :: Other/Proprietary License
Classifier: Programming Language :: Python :: 3
Classifier: Programming Language :: Python :: 3.8
Classifier: Programming Language :: Python :: 3.9
Classifier: Programming Language :: Python :: 3.10
Classifier: Programming Language :: Python :: 3.11
Requires-Dist: ipython (>=8.12.0,<9.0.0)
Requires-Dist: matplotlib (>=3.7.1,<4.0.0)
Requires-Dist: numpy (>=1.24.2,<2.0.0)
Requires-Dist: python-box (>=7.0.1,<8.0.0)
Project-URL: Repository, https://github.com/kxmh42/html-plot
